cwtoken/__init__.py
cwtoken/cli.py
cwtoken/exceptions.py
cwtoken/gui.py
cwtoken/key_manager.py
cwtoken/server.py
cwtoken/utils.py
cwtoken-0.5.0.dist-info/METADATA
cwtoken-0.5.0.dist-info/WHEEL
cwtoken-0.5.0.dist-info/entry_points.txt
cwtoken-0.5.0.dist-info/top_level.txt
cwtoken-0.5.0.dist-info/RECORD
