Metadata-Version: 2.4
Name: cwtoken
Version: 0.5.0
Summary: Package handling tokens and URLs
Author: Connor Crawford
Requires-Python: >=3.7
Requires-Dist: pandas
Requires-Dist: requests
Requires-Dist: click
Requires-Dist: dotenv
Requires-Dist: pathlib
Requires-Dist: flask
Requires-Dist: flask_cors
